example/__init__.py
example/video_grid.py
flet_ivid/__init__.py
flet_ivid/video_container.py
flet_ivid_hks-1.0.dist-info/LICENSE
flet_ivid_hks-1.0.dist-info/METADATA
flet_ivid_hks-1.0.dist-info/WHEEL
flet_ivid_hks-1.0.dist-info/top_level.txt
flet_ivid_hks-1.0.dist-info/RECORD
