Metadata-Version: 2.1
Name: flet-ivid-hks
Version: 1.0
Summary: A package tool that provide basic video player for flet.
Home-page: https://github.com/Uni-Gal/fork-flet_ived
Author: SKbarbon, Hocassian
Classifier: Programming Language :: Python :: 3
Classifier: Operating System :: MacOS :: MacOS X
Classifier: Operating System :: Microsoft :: Windows
License-File: LICENSE
Requires-Dist: flet
Requires-Dist: opencv-python
